Metadata-Version: 2.1
Name: sussyAmogus
Version: 0.2
Summary: a sus pip package
Author: guard_games
Author-email: sourceguy68@gmail.com
Keywords: python,sus,sussy,susamogus,sussy baka,amogus
Classifier: Intended Audience :: Developers
Classifier: Programming Language :: Python :: 3
Classifier: Operating System :: Unix
Classifier: Operating System :: MacOS :: MacOS X
Classifier: Operating System :: Microsoft :: Windows
License-File: LICENSE.txt
